bigone/__init__.py
bigone/client.py
bigone/exceptions.py
python_bigone-0.1.0.dist-info/DESCRIPTION.rst
python_bigone-0.1.0.dist-info/METADATA
python_bigone-0.1.0.dist-info/RECORD
python_bigone-0.1.0.dist-info/WHEEL
python_bigone-0.1.0.dist-info/metadata.json
python_bigone-0.1.0.dist-info/top_level.txt
